// class version 50.0 (50)
// access flags 0x401
public abstract class codechicken/multipart/scalatraits/JCapabilityProvider$class {

  // compiled from: TCapabilityProvider.scala

  // access flags 0x9
  public static ITEM_CAP(Lcodechicken/multipart/scalatraits/JCapabilityProvider;)Lnet/minecraftforge/common/capabilities/Capability;
   L0
    LINENUMBER 107 L0
    ALOAD 0
    INVOKEINTERFACE codechicken/multipart/scalatraits/JCapabilityProvider.codechicken$multipart$scalatraits$JCapabilityProvider$$ITEM_CAP ()Lnet/minecraftforge/common/capabilities/Capability;
    ARETURN
   L1
    LOCALVARIABLE this Lcodechicken/multipart/scalatraits/JCapabilityProvider; L0 L1 0
    MAXSTACK = 1
    MAXLOCALS = 1

  // access flags 0x9
  public static caps(Lcodechicken/multipart/scalatraits/JCapabilityProvider;)Ljava/util/LinkedList;
   L0
    LINENUMBER 107 L0
    ALOAD 0
    INVOKEINTERFACE codechicken/multipart/scalatraits/JCapabilityProvider.codechicken$multipart$scalatraits$JCapabilityProvider$$caps ()Ljava/util/LinkedList;
    ARETURN
   L1
    LOCALVARIABLE this Lcodechicken/multipart/scalatraits/JCapabilityProvider; L0 L1 0
    MAXSTACK = 1
    MAXLOCALS = 1

  // access flags 0x9
  public static caps_$eq(Lcodechicken/multipart/scalatraits/JCapabilityProvider;Ljava/util/LinkedList;)V
  @Lscala/runtime/TraitSetter;()
   L0
    LINENUMBER 107 L0
    ALOAD 0
    ALOAD 1
    INVOKEINTERFACE codechicken/multipart/scalatraits/JCapabilityProvider.codechicken$multipart$scalatraits$JCapabilityProvider$$caps_$eq (Ljava/util/LinkedList;)V
    RETURN
   L1
    LOCALVARIABLE this Lcodechicken/multipart/scalatraits/JCapabilityProvider; L0 L1 0
    LOCALVARIABLE x$1 Ljava/util/LinkedList; L0 L1 1
    MAXSTACK = 2
    MAXLOCALS = 2

  // access flags 0x9
  public static itemCaps(Lcodechicken/multipart/scalatraits/JCapabilityProvider;)[Lcodechicken/multipart/scalatraits/WrappedItemHandler;
   L0
    LINENUMBER 107 L0
    ALOAD 0
    INVOKEINTERFACE codechicken/multipart/scalatraits/JCapabilityProvider.codechicken$multipart$scalatraits$JCapabilityProvider$$itemCaps ()[Lcodechicken/multipart/scalatraits/WrappedItemHandler;
    ARETURN
   L1
    LOCALVARIABLE this Lcodechicken/multipart/scalatraits/JCapabilityProvider; L0 L1 0
    MAXSTACK = 1
    MAXLOCALS = 1

  // access flags 0x9
  public static itemCaps_$eq(Lcodechicken/multipart/scalatraits/JCapabilityProvider;[Lcodechicken/multipart/scalatraits/WrappedItemHandler;)V
  @Lscala/runtime/TraitSetter;()
   L0
    LINENUMBER 107 L0
    ALOAD 0
    ALOAD 1
    INVOKEINTERFACE codechicken/multipart/scalatraits/JCapabilityProvider.codechicken$multipart$scalatraits$JCapabilityProvider$$itemCaps_$eq ([Lcodechicken/multipart/scalatraits/WrappedItemHandler;)V
    RETURN
   L1
    LOCALVARIABLE this Lcodechicken/multipart/scalatraits/JCapabilityProvider; L0 L1 0
    LOCALVARIABLE x$1 [Lcodechicken/multipart/scalatraits/WrappedItemHandler; L0 L1 1
    MAXSTACK = 2
    MAXLOCALS = 2

  // access flags 0x9
  public static genericItemCap(Lcodechicken/multipart/scalatraits/JCapabilityProvider;)Lcodechicken/multipart/scalatraits/WrappedItemHandler;
   L0
    LINENUMBER 107 L0
    ALOAD 0
    INVOKEINTERFACE codechicken/multipart/scalatraits/JCapabilityProvider.codechicken$multipart$scalatraits$JCapabilityProvider$$genericItemCap ()Lcodechicken/multipart/scalatraits/WrappedItemHandler;
    ARETURN
   L1
    LOCALVARIABLE this Lcodechicken/multipart/scalatraits/JCapabilityProvider; L0 L1 0
    MAXSTACK = 1
    MAXLOCALS = 1

  // access flags 0x9
  public static genericItemCap_$eq(Lcodechicken/multipart/scalatraits/JCapabilityProvider;Lcodechicken/multipart/scalatraits/WrappedItemHandler;)V
  @Lscala/runtime/TraitSetter;()
   L0
    LINENUMBER 107 L0
    ALOAD 0
    ALOAD 1
    INVOKEINTERFACE codechicken/multipart/scalatraits/JCapabilityProvider.codechicken$multipart$scalatraits$JCapabilityProvider$$genericItemCap_$eq (Lcodechicken/multipart/scalatraits/WrappedItemHandler;)V
    RETURN
   L1
    LOCALVARIABLE this Lcodechicken/multipart/scalatraits/JCapabilityProvider; L0 L1 0
    LOCALVARIABLE x$1 Lcodechicken/multipart/scalatraits/WrappedItemHandler; L0 L1 1
    MAXSTACK = 2
    MAXLOCALS = 2

  // access flags 0x9
  public static codechicken$multipart$scalatraits$TCapabilityProvider$$super$copyFrom(Lcodechicken/multipart/scalatraits/JCapabilityProvider;Lcodechicken/multipart/TileMultipart;)V
   L0
    LINENUMBER 107 L0
    ALOAD 0
    ALOAD 1
    INVOKEINTERFACE codechicken/multipart/scalatraits/JCapabilityProvider.codechicken$multipart$scalatraits$JCapabilityProvider$$super$copyFrom (Lcodechicken/multipart/TileMultipart;)V
    RETURN
   L1
    LOCALVARIABLE this Lcodechicken/multipart/scalatraits/JCapabilityProvider; L0 L1 0
    LOCALVARIABLE that Lcodechicken/multipart/TileMultipart; L0 L1 1
    MAXSTACK = 2
    MAXLOCALS = 2

  // access flags 0x9
  public static codechicken$multipart$scalatraits$TCapabilityProvider$$super$bindPart(Lcodechicken/multipart/scalatraits/JCapabilityProvider;Lcodechicken/multipart/TMultiPart;)V
   L0
    LINENUMBER 107 L0
    ALOAD 0
    ALOAD 1
    INVOKEINTERFACE codechicken/multipart/scalatraits/JCapabilityProvider.codechicken$multipart$scalatraits$JCapabilityProvider$$super$bindPart (Lcodechicken/multipart/TMultiPart;)V
    RETURN
   L1
    LOCALVARIABLE this Lcodechicken/multipart/scalatraits/JCapabilityProvider; L0 L1 0
    LOCALVARIABLE part Lcodechicken/multipart/TMultiPart; L0 L1 1
    MAXSTACK = 2
    MAXLOCALS = 2

  // access flags 0x9
  public static codechicken$multipart$scalatraits$TCapabilityProvider$$super$clearParts(Lcodechicken/multipart/scalatraits/JCapabilityProvider;)V
   L0
    LINENUMBER 107 L0
    ALOAD 0
    INVOKEINTERFACE codechicken/multipart/scalatraits/JCapabilityProvider.codechicken$multipart$scalatraits$JCapabilityProvider$$super$clearParts ()V
    RETURN
   L1
    LOCALVARIABLE this Lcodechicken/multipart/scalatraits/JCapabilityProvider; L0 L1 0
    MAXSTACK = 1
    MAXLOCALS = 1

  // access flags 0x9
  public static codechicken$multipart$scalatraits$TCapabilityProvider$$super$hasCapability(Lcodechicken/multipart/scalatraits/JCapabilityProvider;Lnet/minecraftforge/common/capabilities/Capability;Lnet/minecraft/util/EnumFacing;)Z
   L0
    LINENUMBER 107 L0
    ALOAD 0
    ALOAD 1
    ALOAD 2
    INVOKEINTERFACE codechicken/multipart/scalatraits/JCapabilityProvider.codechicken$multipart$scalatraits$JCapabilityProvider$$super$hasCapability (Lnet/minecraftforge/common/capabilities/Capability;Lnet/minecraft/util/EnumFacing;)Z
    IRETURN
   L1
    LOCALVARIABLE this Lcodechicken/multipart/scalatraits/JCapabilityProvider; L0 L1 0
    LOCALVARIABLE x$1 Lnet/minecraftforge/common/capabilities/Capability; L0 L1 1
    LOCALVARIABLE x$2 Lnet/minecraft/util/EnumFacing; L0 L1 2
    MAXSTACK = 3
    MAXLOCALS = 3

  // access flags 0x9
  public static codechicken$multipart$scalatraits$TCapabilityProvider$$super$getCapability(Lcodechicken/multipart/scalatraits/JCapabilityProvider;Lnet/minecraftforge/common/capabilities/Capability;Lnet/minecraft/util/EnumFacing;)Ljava/lang/Object;
   L0
    LINENUMBER 107 L0
    ALOAD 0
    ALOAD 1
    ALOAD 2
    INVOKEINTERFACE codechicken/multipart/scalatraits/JCapabilityProvider.codechicken$multipart$scalatraits$JCapabilityProvider$$super$getCapability (Lnet/minecraftforge/common/capabilities/Capability;Lnet/minecraft/util/EnumFacing;)Ljava/lang/Object;
    ARETURN
   L1
    LOCALVARIABLE this Lcodechicken/multipart/scalatraits/JCapabilityProvider; L0 L1 0
    LOCALVARIABLE x$1 Lnet/minecraftforge/common/capabilities/Capability; L0 L1 1
    LOCALVARIABLE x$2 Lnet/minecraft/util/EnumFacing; L0 L1 2
    MAXSTACK = 3
    MAXLOCALS = 3

  // access flags 0x9
  public static codechicken$multipart$scalatraits$TCapabilityProvider$_setter_$ITEM_CAP_$eq(Lcodechicken/multipart/scalatraits/JCapabilityProvider;Lnet/minecraftforge/common/capabilities/Capability;)V
   L0
    LINENUMBER 107 L0
    ALOAD 0
    ALOAD 1
    INVOKEINTERFACE codechicken/multipart/scalatraits/JCapabilityProvider.codechicken$multipart$scalatraits$JCapabilityProvider$$ITEM_CAP_$eq (Lnet/minecraftforge/common/capabilities/Capability;)V
    RETURN
   L1
    LOCALVARIABLE this Lcodechicken/multipart/scalatraits/JCapabilityProvider; L0 L1 0
    LOCALVARIABLE x$1 Lnet/minecraftforge/common/capabilities/Capability; L0 L1 1
    MAXSTACK = 2
    MAXLOCALS = 2

  // access flags 0x9
  public static copyFrom(Lcodechicken/multipart/scalatraits/JCapabilityProvider;Lcodechicken/multipart/TileMultipart;)V
   L0
    LINENUMBER 107 L0
    ALOAD 0
    ALOAD 1
    INVOKESTATIC codechicken/multipart/scalatraits/TCapabilityProvider$class.copyFrom (Lcodechicken/multipart/scalatraits/TCapabilityProvider;Lcodechicken/multipart/TileMultipart;)V
    RETURN
   L1
    LOCALVARIABLE this Lcodechicken/multipart/scalatraits/JCapabilityProvider; L0 L1 0
    LOCALVARIABLE that Lcodechicken/multipart/TileMultipart; L0 L1 1
    MAXSTACK = 2
    MAXLOCALS = 2

  // access flags 0x9
  public static bindPart(Lcodechicken/multipart/scalatraits/JCapabilityProvider;Lcodechicken/multipart/TMultiPart;)V
   L0
    LINENUMBER 107 L0
    ALOAD 0
    ALOAD 1
    INVOKESTATIC codechicken/multipart/scalatraits/TCapabilityProvider$class.bindPart (Lcodechicken/multipart/scalatraits/TCapabilityProvider;Lcodechicken/multipart/TMultiPart;)V
    RETURN
   L1
    LOCALVARIABLE this Lcodechicken/multipart/scalatraits/JCapabilityProvider; L0 L1 0
    LOCALVARIABLE part Lcodechicken/multipart/TMultiPart; L0 L1 1
    MAXSTACK = 2
    MAXLOCALS = 2

  // access flags 0x9
  public static clearParts(Lcodechicken/multipart/scalatraits/JCapabilityProvider;)V
   L0
    LINENUMBER 107 L0
    ALOAD 0
    INVOKESTATIC codechicken/multipart/scalatraits/TCapabilityProvider$class.clearParts (Lcodechicken/multipart/scalatraits/TCapabilityProvider;)V
    RETURN
   L1
    LOCALVARIABLE this Lcodechicken/multipart/scalatraits/JCapabilityProvider; L0 L1 0
    MAXSTACK = 1
    MAXLOCALS = 1

  // access flags 0x9
  public static rebuildSlotMap(Lcodechicken/multipart/scalatraits/JCapabilityProvider;)V
   L0
    LINENUMBER 107 L0
    ALOAD 0
    INVOKESTATIC codechicken/multipart/scalatraits/TCapabilityProvider$class.rebuildSlotMap (Lcodechicken/multipart/scalatraits/TCapabilityProvider;)V
    RETURN
   L1
    LOCALVARIABLE this Lcodechicken/multipart/scalatraits/JCapabilityProvider; L0 L1 0
    MAXSTACK = 1
    MAXLOCALS = 1

  // access flags 0x9
  public static hasCapability(Lcodechicken/multipart/scalatraits/JCapabilityProvider;Lnet/minecraftforge/common/capabilities/Capability;Lnet/minecraft/util/EnumFacing;)Z
   L0
    LINENUMBER 107 L0
    ALOAD 0
    ALOAD 1
    ALOAD 2
    INVOKESTATIC codechicken/multipart/scalatraits/TCapabilityProvider$class.hasCapability (Lcodechicken/multipart/scalatraits/TCapabilityProvider;Lnet/minecraftforge/common/capabilities/Capability;Lnet/minecraft/util/EnumFacing;)Z
    IRETURN
   L1
    LOCALVARIABLE this Lcodechicken/multipart/scalatraits/JCapabilityProvider; L0 L1 0
    LOCALVARIABLE capability Lnet/minecraftforge/common/capabilities/Capability; L0 L1 1
    LOCALVARIABLE side Lnet/minecraft/util/EnumFacing; L0 L1 2
    MAXSTACK = 3
    MAXLOCALS = 3

  // access flags 0x9
  public static getCapability(Lcodechicken/multipart/scalatraits/JCapabilityProvider;Lnet/minecraftforge/common/capabilities/Capability;Lnet/minecraft/util/EnumFacing;)Ljava/lang/Object;
   L0
    LINENUMBER 107 L0
    ALOAD 0
    ALOAD 1
    ALOAD 2
    INVOKESTATIC codechicken/multipart/scalatraits/TCapabilityProvider$class.getCapability (Lcodechicken/multipart/scalatraits/TCapabilityProvider;Lnet/minecraftforge/common/capabilities/Capability;Lnet/minecraft/util/EnumFacing;)Ljava/lang/Object;
    ARETURN
   L1
    LOCALVARIABLE this Lcodechicken/multipart/scalatraits/JCapabilityProvider; L0 L1 0
    LOCALVARIABLE capability Lnet/minecraftforge/common/capabilities/Capability; L0 L1 1
    LOCALVARIABLE side Lnet/minecraft/util/EnumFacing; L0 L1 2
    MAXSTACK = 3
    MAXLOCALS = 3

  // access flags 0x9
  public static $init$(Lcodechicken/multipart/scalatraits/JCapabilityProvider;)V
   L0
    LINENUMBER 107 L0
    ALOAD 0
    INVOKESTATIC codechicken/multipart/scalatraits/TCapabilityProvider$class.$init$ (Lcodechicken/multipart/scalatraits/TCapabilityProvider;)V
    RETURN
   L1
    LOCALVARIABLE this Lcodechicken/multipart/scalatraits/JCapabilityProvider; L0 L1 0
    MAXSTACK = 1
    MAXLOCALS = 1
}
