// class version 50.0 (50)
// access flags 0x401
public abstract class codechicken/multipart/scalatraits/JTickableTile$class {

  // compiled from: TTickableTile.scala

  // access flags 0x9
  public static codechicken$multipart$scalatraits$TTickableTile$$doesTick(Lcodechicken/multipart/scalatraits/JTickableTile;)Z
   L0
    LINENUMBER 95 L0
    ALOAD 0
    INVOKEINTERFACE codechicken/multipart/scalatraits/JTickableTile.codechicken$multipart$scalatraits$JTickableTile$$codechicken$multipart$scalatraits$TTickableTile$$doesTick ()Z
    IRETURN
   L1
    LOCALVARIABLE this Lcodechicken/multipart/scalatraits/JTickableTile; L0 L1 0
    MAXSTACK = 1
    MAXLOCALS = 1

  // access flags 0x9
  public static codechicken$multipart$scalatraits$TTickableTile$$doesTick_$eq(Lcodechicken/multipart/scalatraits/JTickableTile;Z)V
  @Lscala/runtime/TraitSetter;()
   L0
    LINENUMBER 95 L0
    ALOAD 0
    ILOAD 1
    INVOKEINTERFACE codechicken/multipart/scalatraits/JTickableTile.codechicken$multipart$scalatraits$JTickableTile$$codechicken$multipart$scalatraits$TTickableTile$$doesTick_$eq (Z)V
    RETURN
   L1
    LOCALVARIABLE this Lcodechicken/multipart/scalatraits/JTickableTile; L0 L1 0
    LOCALVARIABLE x$1 Z L0 L1 1
    MAXSTACK = 2
    MAXLOCALS = 2

  // access flags 0x9
  public static tickingParts(Lcodechicken/multipart/scalatraits/JTickableTile;)Ljava/util/LinkedList;
   L0
    LINENUMBER 95 L0
    ALOAD 0
    INVOKEINTERFACE codechicken/multipart/scalatraits/JTickableTile.codechicken$multipart$scalatraits$JTickableTile$$tickingParts ()Ljava/util/LinkedList;
    ARETURN
   L1
    LOCALVARIABLE this Lcodechicken/multipart/scalatraits/JTickableTile; L0 L1 0
    MAXSTACK = 1
    MAXLOCALS = 1

  // access flags 0x9
  public static tickingParts_$eq(Lcodechicken/multipart/scalatraits/JTickableTile;Ljava/util/LinkedList;)V
  @Lscala/runtime/TraitSetter;()
   L0
    LINENUMBER 95 L0
    ALOAD 0
    ALOAD 1
    INVOKEINTERFACE codechicken/multipart/scalatraits/JTickableTile.codechicken$multipart$scalatraits$JTickableTile$$tickingParts_$eq (Ljava/util/LinkedList;)V
    RETURN
   L1
    LOCALVARIABLE this Lcodechicken/multipart/scalatraits/JTickableTile; L0 L1 0
    LOCALVARIABLE x$1 Ljava/util/LinkedList; L0 L1 1
    MAXSTACK = 2
    MAXLOCALS = 2

  // access flags 0x9
  public static codechicken$multipart$scalatraits$TTickableTile$$super$copyFrom(Lcodechicken/multipart/scalatraits/JTickableTile;Lcodechicken/multipart/TileMultipart;)V
   L0
    LINENUMBER 95 L0
    ALOAD 0
    ALOAD 1
    INVOKEINTERFACE codechicken/multipart/scalatraits/JTickableTile.codechicken$multipart$scalatraits$JTickableTile$$super$copyFrom (Lcodechicken/multipart/TileMultipart;)V
    RETURN
   L1
    LOCALVARIABLE this Lcodechicken/multipart/scalatraits/JTickableTile; L0 L1 0
    LOCALVARIABLE that Lcodechicken/multipart/TileMultipart; L0 L1 1
    MAXSTACK = 2
    MAXLOCALS = 2

  // access flags 0x9
  public static codechicken$multipart$scalatraits$TTickableTile$$super$bindPart(Lcodechicken/multipart/scalatraits/JTickableTile;Lcodechicken/multipart/TMultiPart;)V
   L0
    LINENUMBER 95 L0
    ALOAD 0
    ALOAD 1
    INVOKEINTERFACE codechicken/multipart/scalatraits/JTickableTile.codechicken$multipart$scalatraits$JTickableTile$$super$bindPart (Lcodechicken/multipart/TMultiPart;)V
    RETURN
   L1
    LOCALVARIABLE this Lcodechicken/multipart/scalatraits/JTickableTile; L0 L1 0
    LOCALVARIABLE part Lcodechicken/multipart/TMultiPart; L0 L1 1
    MAXSTACK = 2
    MAXLOCALS = 2

  // access flags 0x9
  public static codechicken$multipart$scalatraits$TTickableTile$$super$partRemoved(Lcodechicken/multipart/scalatraits/JTickableTile;Lcodechicken/multipart/TMultiPart;I)V
   L0
    LINENUMBER 95 L0
    ALOAD 0
    ALOAD 1
    ILOAD 2
    INVOKEINTERFACE codechicken/multipart/scalatraits/JTickableTile.codechicken$multipart$scalatraits$JTickableTile$$super$partRemoved (Lcodechicken/multipart/TMultiPart;I)V
    RETURN
   L1
    LOCALVARIABLE this Lcodechicken/multipart/scalatraits/JTickableTile; L0 L1 0
    LOCALVARIABLE part Lcodechicken/multipart/TMultiPart; L0 L1 1
    LOCALVARIABLE p I L0 L1 2
    MAXSTACK = 3
    MAXLOCALS = 3

  // access flags 0x9
  public static codechicken$multipart$scalatraits$TTickableTile$$super$clearParts(Lcodechicken/multipart/scalatraits/JTickableTile;)V
   L0
    LINENUMBER 95 L0
    ALOAD 0
    INVOKEINTERFACE codechicken/multipart/scalatraits/JTickableTile.codechicken$multipart$scalatraits$JTickableTile$$super$clearParts ()V
    RETURN
   L1
    LOCALVARIABLE this Lcodechicken/multipart/scalatraits/JTickableTile; L0 L1 0
    MAXSTACK = 1
    MAXLOCALS = 1

  // access flags 0x9
  public static codechicken$multipart$scalatraits$TTickableTile$$super$loadFrom(Lcodechicken/multipart/scalatraits/JTickableTile;Lcodechicken/multipart/TileMultipart;)V
   L0
    LINENUMBER 95 L0
    ALOAD 0
    ALOAD 1
    INVOKEINTERFACE codechicken/multipart/scalatraits/JTickableTile.codechicken$multipart$scalatraits$JTickableTile$$super$loadFrom (Lcodechicken/multipart/TileMultipart;)V
    RETURN
   L1
    LOCALVARIABLE this Lcodechicken/multipart/scalatraits/JTickableTile; L0 L1 0
    LOCALVARIABLE that Lcodechicken/multipart/TileMultipart; L0 L1 1
    MAXSTACK = 2
    MAXLOCALS = 2

  // access flags 0x9
  public static codechicken$multipart$scalatraits$TTickableTile$$super$loadTo(Lcodechicken/multipart/scalatraits/JTickableTile;Lcodechicken/multipart/TileMultipart;)V
   L0
    LINENUMBER 95 L0
    ALOAD 0
    ALOAD 1
    INVOKEINTERFACE codechicken/multipart/scalatraits/JTickableTile.codechicken$multipart$scalatraits$JTickableTile$$super$loadTo (Lcodechicken/multipart/TileMultipart;)V
    RETURN
   L1
    LOCALVARIABLE this Lcodechicken/multipart/scalatraits/JTickableTile; L0 L1 0
    LOCALVARIABLE that Lcodechicken/multipart/TileMultipart; L0 L1 1
    MAXSTACK = 2
    MAXLOCALS = 2

  // access flags 0x9
  public static copyFrom(Lcodechicken/multipart/scalatraits/JTickableTile;Lcodechicken/multipart/TileMultipart;)V
   L0
    LINENUMBER 95 L0
    ALOAD 0
    ALOAD 1
    INVOKESTATIC codechicken/multipart/scalatraits/TTickableTile$class.copyFrom (Lcodechicken/multipart/scalatraits/TTickableTile;Lcodechicken/multipart/TileMultipart;)V
    RETURN
   L1
    LOCALVARIABLE this Lcodechicken/multipart/scalatraits/JTickableTile; L0 L1 0
    LOCALVARIABLE that Lcodechicken/multipart/TileMultipart; L0 L1 1
    MAXSTACK = 2
    MAXLOCALS = 2

  // access flags 0x9
  public static bindPart(Lcodechicken/multipart/scalatraits/JTickableTile;Lcodechicken/multipart/TMultiPart;)V
   L0
    LINENUMBER 95 L0
    ALOAD 0
    ALOAD 1
    INVOKESTATIC codechicken/multipart/scalatraits/TTickableTile$class.bindPart (Lcodechicken/multipart/scalatraits/TTickableTile;Lcodechicken/multipart/TMultiPart;)V
    RETURN
   L1
    LOCALVARIABLE this Lcodechicken/multipart/scalatraits/JTickableTile; L0 L1 0
    LOCALVARIABLE part Lcodechicken/multipart/TMultiPart; L0 L1 1
    MAXSTACK = 2
    MAXLOCALS = 2

  // access flags 0x9
  public static partRemoved(Lcodechicken/multipart/scalatraits/JTickableTile;Lcodechicken/multipart/TMultiPart;I)V
   L0
    LINENUMBER 95 L0
    ALOAD 0
    ALOAD 1
    ILOAD 2
    INVOKESTATIC codechicken/multipart/scalatraits/TTickableTile$class.partRemoved (Lcodechicken/multipart/scalatraits/TTickableTile;Lcodechicken/multipart/TMultiPart;I)V
    RETURN
   L1
    LOCALVARIABLE this Lcodechicken/multipart/scalatraits/JTickableTile; L0 L1 0
    LOCALVARIABLE part Lcodechicken/multipart/TMultiPart; L0 L1 1
    LOCALVARIABLE p I L0 L1 2
    MAXSTACK = 3
    MAXLOCALS = 3

  // access flags 0x9
  public static clearParts(Lcodechicken/multipart/scalatraits/JTickableTile;)V
   L0
    LINENUMBER 95 L0
    ALOAD 0
    INVOKESTATIC codechicken/multipart/scalatraits/TTickableTile$class.clearParts (Lcodechicken/multipart/scalatraits/TTickableTile;)V
    RETURN
   L1
    LOCALVARIABLE this Lcodechicken/multipart/scalatraits/JTickableTile; L0 L1 0
    MAXSTACK = 1
    MAXLOCALS = 1

  // access flags 0x9
  public static update(Lcodechicken/multipart/scalatraits/JTickableTile;)V
   L0
    LINENUMBER 95 L0
    ALOAD 0
    INVOKESTATIC codechicken/multipart/scalatraits/TTickableTile$class.update (Lcodechicken/multipart/scalatraits/TTickableTile;)V
    RETURN
   L1
    LOCALVARIABLE this Lcodechicken/multipart/scalatraits/JTickableTile; L0 L1 0
    MAXSTACK = 1
    MAXLOCALS = 1

  // access flags 0x9
  public static loadFrom(Lcodechicken/multipart/scalatraits/JTickableTile;Lcodechicken/multipart/TileMultipart;)V
   L0
    LINENUMBER 95 L0
    ALOAD 0
    ALOAD 1
    INVOKESTATIC codechicken/multipart/scalatraits/TTickableTile$class.loadFrom (Lcodechicken/multipart/scalatraits/TTickableTile;Lcodechicken/multipart/TileMultipart;)V
    RETURN
   L1
    LOCALVARIABLE this Lcodechicken/multipart/scalatraits/JTickableTile; L0 L1 0
    LOCALVARIABLE that Lcodechicken/multipart/TileMultipart; L0 L1 1
    MAXSTACK = 2
    MAXLOCALS = 2

  // access flags 0x9
  public static loadTo(Lcodechicken/multipart/scalatraits/JTickableTile;Lcodechicken/multipart/TileMultipart;)V
   L0
    LINENUMBER 95 L0
    ALOAD 0
    ALOAD 1
    INVOKESTATIC codechicken/multipart/scalatraits/TTickableTile$class.loadTo (Lcodechicken/multipart/scalatraits/TTickableTile;Lcodechicken/multipart/TileMultipart;)V
    RETURN
   L1
    LOCALVARIABLE this Lcodechicken/multipart/scalatraits/JTickableTile; L0 L1 0
    LOCALVARIABLE that Lcodechicken/multipart/TileMultipart; L0 L1 1
    MAXSTACK = 2
    MAXLOCALS = 2

  // access flags 0x9
  public static $init$(Lcodechicken/multipart/scalatraits/JTickableTile;)V
   L0
    LINENUMBER 95 L0
    ALOAD 0
    INVOKESTATIC codechicken/multipart/scalatraits/TTickableTile$class.$init$ (Lcodechicken/multipart/scalatraits/TTickableTile;)V
    RETURN
   L1
    LOCALVARIABLE this Lcodechicken/multipart/scalatraits/JTickableTile; L0 L1 0
    MAXSTACK = 1
    MAXLOCALS = 1
}
